{
  "os": "Linux-6.8.0-48-generic-x86_64-with-glibc2.39",
  "python": "3.12.3",
  "startedAt": "2024-11-21T20:15:11.398763Z",
  "program": "Untitled-1.ipynb",
  "git": {
    "remote": "https://gitlab.com/hongzhangsun/transportation-2024.git",
    "commit": "941dc97d770b280120941e202b3638e3af9b8e86"
  },
  "email": "duantu97@gmail.com",
  "root": "/home/duantu/soft/transportation-2024/notebooks",
  "host": "duantu-ThinkPad-T14s-Gen-3",
  "username": "duantu",
  "executable": "/home/duantu/soft/transportation_venv/bin/python3",
  "cpu_count": 8,
  "cpu_count_logical": 16,
  "disk": {
    "/": {
      "total": "502392610816",
      "used": "202182295552"
    }
  },
  "memory": {
    "total": "32347926528"
  },
  "cpu": {
    "count": 8,
    "countLogical": 16
  }
}